TEStribute/__init__.py
TEStribute/__main__.py
TEStribute/cli.py
TEStribute/server.py
TEStribute/config/__init__.py
TEStribute/config/config.yaml
TEStribute/controllers/__init__.py
TEStribute/decorators/__init__.py
TEStribute/errors/__init__.py
TEStribute/log/__init__.py
TEStribute/models/__init__.py
TEStribute/models/request.py
TEStribute/models/response.py
TEStribute/security/process_jwt.py
TEStribute/specs/schema.TEStribute.openapi.yaml
TEStribute/utils/service_calls.py
TEStribute-0.2.1.dist-info/LICENSE
TEStribute-0.2.1.dist-info/METADATA
TEStribute-0.2.1.dist-info/WHEEL
TEStribute-0.2.1.dist-info/entry_points.txt
TEStribute-0.2.1.dist-info/top_level.txt
TEStribute-0.2.1.dist-info/RECORD
