Metadata-Version: 2.1
Name: TEStribute
Version: 0.2.1
Summary: Task distribution for GA4GH TES instances
Home-page: https://github.com/elixir-europe/TEStribute
Author: ELIXIR Cloud & AAI
Author-email: alexander.kanitz@alumni.ethz.ch
Maintainer: Alexander Kanitz
Maintainer-email: alexander.kanitz@alumnni.ethz.ch
License: UNKNOWN
Project-URL: Repository, https://github.com/elixir-europe/TEStribute
Project-URL: ELIXIR Cloud & AAI, https://elixir-europe.github.io/cloud/
Project-URL: Tracker, https://github.com/elixir-europe/TEStribute/issues
Keywords: ga4gh tes elixir rest api app openapi python task distribution
Platform: UNKNOWN
Classifier: Development Status :: 3 - Alpha
Classifier: Environment :: Console
Classifier: Environment :: Web Environment
Classifier: Framework :: Flask
Classifier: Intended Audience :: Developers
Classifier: Intended Audience :: Healthcare Industry
Classifier: Intended Audience :: Information Technology
Classifier: Intended Audience :: Science/Research
Classifier: Intended Audience :: System Administrators
Classifier: License :: OSI Approved :: Apache Software License
Classifier: Natural Language :: English
Classifier: Programming Language :: Python :: 3 :: Only
Classifier: Topic :: Internet :: WWW/HTTP
Classifier: Topic :: Scientific/Engineering :: Bio-Informatics
Classifier: Topic :: Scientific/Engineering :: Medical Science Apps.
Classifier: Topic :: System :: Systems Administration
Classifier: Topic :: Utilities
Classifier: Typing :: Typed
Requires-Python: ~=3.6
Requires-Dist: addict (==2.2.0)
Requires-Dist: asn1crypto (==0.24.0)
Requires-Dist: astroid (==2.2.5)
Requires-Dist: atomicwrites (==1.3.0)
Requires-Dist: attrs (==19.1.0)
Requires-Dist: Automat (==0.7.0)
Requires-Dist: autopep8 (==1.4.4)
Requires-Dist: bleach (==3.1.0)
Requires-Dist: bravado (==10.4.1)
Requires-Dist: bravado-core (==5.13.1)
Requires-Dist: certifi (==2019.6.16)
Requires-Dist: cffi (==1.12.3)
Requires-Dist: chardet (==3.0.4)
Requires-Dist: Click (==7.0)
Requires-Dist: clickclick (==1.2.2)
Requires-Dist: connexion (==2.3.0)
Requires-Dist: constantly (==15.1.0)
Requires-Dist: crochet (==1.10.0)
Requires-Dist: cryptography (==2.7)
Requires-Dist: cssselect (==1.0.3)
Requires-Dist: decorator (==4.4.0)
Requires-Dist: dicttoxml (==1.7.4)
Requires-Dist: docutils (==0.15.2)
Requires-Dist: drs-client (==0.2.0)
Requires-Dist: fido (==4.2.2)
Requires-Dist: Flask (==1.1.1)
Requires-Dist: forex-python (==1.5)
Requires-Dist: future (==0.17.1)
Requires-Dist: geocoder (==1.38.1)
Requires-Dist: geographiclib (==1.49)
Requires-Dist: geoip2 (==2.9.0)
Requires-Dist: geopy (==1.20.0)
Requires-Dist: hyperlink (==19.0.0)
Requires-Dist: idna (==2.8)
Requires-Dist: importlib-metadata (==0.19)
Requires-Dist: incremental (==17.5.0)
Requires-Dist: inflection (==0.3.1)
Requires-Dist: ip2geotools (==0.1.5)
Requires-Dist: IP2Location (==8.1.0)
Requires-Dist: isort (==4.3.21)
Requires-Dist: itsdangerous (==1.1.0)
Requires-Dist: Jinja2 (==2.10.1)
Requires-Dist: jsonpointer (==2.0)
Requires-Dist: jsonref (==0.2)
Requires-Dist: jsonschema (==2.6.0)
Requires-Dist: lazy-object-proxy (==1.4.1)
Requires-Dist: lxml (==4.3.4)
Requires-Dist: MarkupSafe (==1.1.1)
Requires-Dist: maxminddb (==1.4.1)
Requires-Dist: mccabe (==0.6.1)
Requires-Dist: monotonic (==1.5)
Requires-Dist: more-itertools (==7.2.0)
Requires-Dist: msgpack-python (==0.5.6)
Requires-Dist: numpy (==1.17.2)
Requires-Dist: openapi-spec-validator (==0.2.8)
Requires-Dist: packaging (==19.0)
Requires-Dist: pip-review (==1.0)
Requires-Dist: pkginfo (==1.5.0.1)
Requires-Dist: pluggy (==0.12.0)
Requires-Dist: py (==1.8.0)
Requires-Dist: pycodestyle (==2.5.0)
Requires-Dist: pycparser (==2.19)
Requires-Dist: Pygments (==2.4.2)
Requires-Dist: PyHamcrest (==1.9.0)
Requires-Dist: PyJWT (==1.6.4)
Requires-Dist: pylint (==2.3.1)
Requires-Dist: pyparsing (==2.4.1.1)
Requires-Dist: pyquery (==1.4.0)
Requires-Dist: pyrsistent (==0.15.3)
Requires-Dist: pytest (==5.0.1)
Requires-Dist: python-dateutil (==2.8.0)
Requires-Dist: pytz (==2019.1)
Requires-Dist: PyYAML (==5.1.1)
Requires-Dist: ratelim (==0.1.6)
Requires-Dist: readme-renderer (==24.0)
Requires-Dist: requests (==2.22.0)
Requires-Dist: requests-toolbelt (==0.9.1)
Requires-Dist: rfc3987 (==1.3.8)
Requires-Dist: selenium (==3.141.0)
Requires-Dist: setuptools-git (==1.2)
Requires-Dist: simplejson (==3.16.0)
Requires-Dist: six (==1.12.0)
Requires-Dist: strict-rfc3339 (==0.7)
Requires-Dist: swagger-spec-validator (==2.4.3)
Requires-Dist: swagger-ui-bundle (==0.0.5)
Requires-Dist: tes-client (==0.2.1)
Requires-Dist: tqdm (==4.32.2)
Requires-Dist: twine (==1.13.0)
Requires-Dist: Twisted (==19.7.0)
Requires-Dist: typed-ast (==1.4.0)
Requires-Dist: typing (==3.7.4)
Requires-Dist: typing-extensions (==3.7.4)
Requires-Dist: urllib3 (==1.25.3)
Requires-Dist: wcwidth (==0.1.7)
Requires-Dist: webcolors (==1.9.1)
Requires-Dist: webencodings (==0.5.1)
Requires-Dist: Werkzeug (==0.15.6)
Requires-Dist: wrapt (==1.11.2)
Requires-Dist: yelp-bytes (==0.3.0)
Requires-Dist: yelp-encodings (==0.1.3)
Requires-Dist: zipp (==0.5.2)
Requires-Dist: zope.interface (==4.6.0)
